repolyze/__init__.py
repolyze/cli/__init__.py
repolyze/cli/main.py
repolyze/core/__init__.py
repolyze/core/analyze.py
repolyze/core/filesystem/__init__.py
repolyze/core/filesystem/paths.py
repolyze/core/filesystem/scan.py
repolyze/core/formatting/__init__.py
repolyze/core/formatting/human.py
repolyze/core/formatting/tree.py
repolyze/core/stats/__init__.py
repolyze/core/tree/build.py
repolyze/models/__init__.py
repolyze/models/repo.py
repolyze-0.1.0.dist-info/METADATA
repolyze-0.1.0.dist-info/WHEEL
repolyze-0.1.0.dist-info/entry_points.txt
repolyze-0.1.0.dist-info/licenses/LICENSE
repolyze-0.1.0.dist-info/licenses/NOTICE
repolyze-0.1.0.dist-info/RECORD
