Metadata-Version: 2.4
Name: repolyze
Version: 0.1.0
Summary: Repo statistics
Author-email: Dheeraj Bhat <dheerajnbhat@gmail.com>
Maintainer-email: Dheeraj Bhat <dheerajnbhat@gmail.com>
License-File: LICENSE
License-File: NOTICE
Keywords: repo,repo statistics,repolyze,statistics,stats
Classifier: Intended Audience :: Developers
Classifier: Programming Language :: Python :: 3 :: Only
Requires-Python: >=3.9
